AUTHORS.rst
CONTRIBUTING.rst
HISTORY.rst
LICENSE.txt
MANIFEST.in
README.rst
setup.cfg
setup.py
versioneer.py
docs/Makefile
docs/api.rst
docs/authors.rst
docs/conf.py
docs/contributing.rst
docs/history.rst
docs/index.rst
docs/installation.rst
docs/make.bat
docs/readme.rst
docs/usage.rst
metawrap/__init__.py
metawrap/_version.py
metawrap/metawrap.py
metawrap.egg-info/PKG-INFO
metawrap.egg-info/SOURCES.txt
metawrap.egg-info/dependency_links.txt
metawrap.egg-info/not-zip-safe
metawrap.egg-info/top_level.txt
tests/__init__.py
tests/test_metawrap.py